README
setup.cfg
setup.py
async_netcdf.egg-info/PKG-INFO
async_netcdf.egg-info/SOURCES.txt
async_netcdf.egg-info/dependency_links.txt
async_netcdf.egg-info/entry_points.txt
async_netcdf.egg-info/not-zip-safe
async_netcdf.egg-info/requires.txt
async_netcdf.egg-info/top_level.txt
lib/__init__.py
lib/async_netcdf.py