Metadata-Version: 1.1
Name: async-netcdf
Version: 0.1.1
Summary: Simple BASH compiler to parallelize some netcdf file operations
Home-page: http://proj.badc.rl.ac.uk/exarch
Author: F. B. Laliberté, P. J. Kushner
Author-email: frederic.laliberte@utoronto.ca
License: BSD
Keywords: atmosphere climate
Platform: UNKNOWN
Classifier: Development Status :: 4 - Beta
Classifier: Intended Audience :: Science/Research
Classifier: Natural Language :: English
Classifier: License :: OSI Approved :: BSD License
Classifier: Programming Language :: Python :: 2.7
Classifier: Programming Language :: Fortran
Classifier: Topic :: Scientific/Engineering :: Atmospheric Science
Classifier: Topic :: Scientific/Engineering :: Mathematics
